ResourceBundle/__init__.py
ResourceBundle/exceptions.py
ResourceBundle-2.2.0.dist-info/LICENSE
ResourceBundle-2.2.0.dist-info/METADATA
ResourceBundle-2.2.0.dist-info/WHEEL
ResourceBundle-2.2.0.dist-info/top_level.txt
ResourceBundle-2.2.0.dist-info/RECORD
