Metadata-Version: 2.1
Name: ResourceBundle
Version: 2.2.0
Summary: ResourceBundle is a module that manages internationalization of string resources.
Home-page: https://github.com/felix-zenk/ResourceBundle
Author: Felix Zenk
Author-email: Felix Zenk <felix.zenk@web.de>
License: MIT
Project-URL: Homepage, https://github.com/felix-zenk/ResourceBundle
Project-URL: Documentation, https://github.com/felix-zenk/ResourceBundle
Project-URL: Repository, https://github.com/felix-zenk/ResourceBundle
Project-URL: Issues, https://github.com/felix-zenk/ResourceBundle/issues
Classifier: Programming Language :: Python :: 3
Classifier: Programming Language :: Python :: 3.5
Classifier: Programming Language :: Python :: 3.6
Classifier: Programming Language :: Python :: 3.7
Classifier: Programming Language :: Python :: 3.8
Classifier: Programming Language :: Python :: 3.9
Classifier: Programming Language :: Python :: 3.10
Classifier: Programming Language :: Python :: 3.11
Classifier: Programming Language :: Python :: 3.12
Classifier: Programming Language :: Python :: 3.13
Classifier: Topic :: Utilities
Classifier: License :: OSI Approved :: MIT License
Classifier: Operating System :: OS Independent
Requires-Python: >=3.5
License-File: LICENSE
Requires-Dist: importlib-metadata ; python_version < "3.8"
